LICENSE
README.md
pyproject.toml
setup.cfg
setup.py
examples/__init__.py
examples/manage_invoice.py
examples/manage_shop.py
pyaiolava/__init__.py
pyaiolava/business_lava.py
pyaiolava/constants.py
pyaiolava/exceptions.py
pyaiolava.egg-info/PKG-INFO
pyaiolava.egg-info/SOURCES.txt
pyaiolava.egg-info/dependency_links.txt
pyaiolava.egg-info/requires.txt
pyaiolava.egg-info/top_level.txt
pyaiolava/enums/__init__.py
pyaiolava/enums/endpoint.py
pyaiolava/enums/error.py
pyaiolava/enums/status.py
pyaiolava/factory/__init__.py
pyaiolava/factory/http.py
pyaiolava/factory/invoice_api.py
pyaiolava/factory/payoff_api.py
pyaiolava/factory/recurrent_api.py
pyaiolava/factory/shop_api.py
pyaiolava/models/__init__.py
pyaiolava/models/invoice.py
pyaiolava/models/shop.py
pyaiolava/utils/__init__.py
pyaiolava/utils/converters/__init__.py
pyaiolava/utils/converters/str2datetime.py
pyaiolava/utils/generators/__init__.py
pyaiolava/utils/generators/generate_payment_id.py
pyaiolava/utils/generators/generate_signature.py
pyaiolava/utils/validators/__init__.py
pyaiolava/utils/validators/validate_amount.py
pyaiolava/utils/validators/validate_payment_time.py
pyaiolava/utils/validators/validate_signature.py