Metadata-Version: 2.1
Name: pyaiolava
Version: 0.1.2
Summary: Simple and convenient asynchronous library for working with the Business Lava API.
Home-page: https://github.com/kesevone/aiolava
Author: kesevone
Author-email: kesevone@gmail.com
Project-URL: Official documentation, https://dev.lava.ru/
Keywords: lava aiolava lavaapi pyaiolava businesslava
Classifier: Programming Language :: Python :: 3.11
Classifier: License :: OSI Approved :: MIT License
Classifier: Operating System :: OS Independent
Requires-Python: >=3.10
License-File: LICENSE
Requires-Dist: aiohttp==3.9.3
Requires-Dist: pydantic==2.5.3
